{".class": "MypyFile", "_fullname": "douban.pipelines", "_name": null, "is_stub": false, "names": {".class": "SymbolTable", "DefaultItemPipeline": {".class": "SymbolTableNode", "kind": "Gdef", "node": {".class": "TypeInfo", "_promote": null, "abstract_attributes": [], "bases": ["builtins.object"], "declared_metaclass": null, "defn": {".class": "ClassDef", "fullname": "douban.pipelines.DefaultItemPipeline", "name": "DefaultItemPipeline", "type_vars": []}, "flags": [], "fullname": "douban.pipelines.DefaultItemPipeline", "metaclass_type": null, "module_name": "douban.pipelines", "names": {".class": "SymbolTable", "process_item": {".class": "SymbolTableNode", "kind": "Mdef", "node": {".class": "FuncDef", "arg_kinds": [0, 0, 0], "arg_names": ["self", "item", "spider"], "flags": [], "fullname": "douban.pipelines.DefaultItemPipeline.process_item", "name": "process_item", "type": null}}}, "protocol_members": null, "tuple_type": null, "type_vars": [], "typeddict_type": null}}, "MongoPipeline": {".class": "SymbolTableNode", "kind": "Gdef", "node": {".class": "TypeInfo", "_promote": null, "abstract_attributes": [], "bases": ["builtins.object"], "declared_metaclass": null, "defn": {".class": "ClassDef", "fullname": "douban.pipelines.MongoPipeline", "name": "MongoPipeline", "type_vars": []}, "flags": [], "fullname": "douban.pipelines.MongoPipeline", "metaclass_type": null, "module_name": "douban.pipelines", "names": {".class": "SymbolTable", "__init__": {".class": "SymbolTableNode", "kind": "Mdef", "node": {".class": "FuncDef", "arg_kinds": [0, 0, 0], "arg_names": ["self", "mongo_uri", "mongo_db"], "flags": [], "fullname": "douban.pipelines.MongoPipeline.__init__", "name": "__init__", "type": null}}, "client": {".class": "SymbolTableNode", "implicit": true, "kind": "Mdef", "node": {".class": "Var", "flags": [], "fullname": "douban.pipelines.MongoPipeline.client", "name": "client", "type": {".class": "AnyType"}}}, "close_spider": {".class": "SymbolTableNode", "kind": "Mdef", "node": {".class": "FuncDef", "arg_kinds": [0, 0], "arg_names": ["self", "spider"], "flags": [], "fullname": "douban.pipelines.MongoPipeline.close_spider", "name": "close_spider", "type": null}}, "collection_name": {".class": "SymbolTableNode", "kind": "Mdef", "node": {".class": "Var", "flags": ["is_ready", "is_initialized_in_class"], "fullname": "douban.pipelines.MongoPipeline.collection_name", "name": "collection_name", "type": "builtins.str"}}, "db": {".class": "SymbolTableNode", "implicit": true, "kind": "Mdef", "node": {".class": "Var", "flags": [], "fullname": "douban.pipelines.MongoPipeline.db", "name": "db", "type": {".class": "AnyType"}}}, "from_crawler": {".class": "SymbolTableNode", "kind": "Mdef", "node": {".class": "Decorator", "func": {".class": "FuncDef", "arg_kinds": [0, 0], "arg_names": ["cls", "crawler"], "flags": ["is_class", "is_decorated"], "fullname": "douban.pipelines.MongoPipeline.from_crawler", "name": "from_crawler", "type": null}, "is_overload": false, "var": {".class": "Var", "flags": ["is_ready", "is_initialized_in_class", "is_classmethod"], "fullname": null, "name": "from_crawler", "type": {".class": "CallableType", "arg_kinds": [0, 0], "arg_names": ["cls", "crawler"], "arg_types": [{".class": "AnyType"}, {".class": "AnyType"}], "bound_args": [], "fallback": "builtins.function", "implicit": true, "is_classmethod_class": false, "is_ellipsis_args": false, "name": "from_crawler of MongoPipeline", "ret_type": {".class": "AnyType"}, "variables": []}}}}, "mongo_db": {".class": "SymbolTableNode", "implicit": true, "kind": "Mdef", "node": {".class": "Var", "flags": [], "fullname": "douban.pipelines.MongoPipeline.mongo_db", "name": "mongo_db", "type": {".class": "AnyType"}}}, "mongo_uri": {".class": "SymbolTableNode", "implicit": true, "kind": "Mdef", "node": {".class": "Var", "flags": [], "fullname": "douban.pipelines.MongoPipeline.mongo_uri", "name": "mongo_uri", "type": {".class": "AnyType"}}}, "open_spider": {".class": "SymbolTableNode", "kind": "Mdef", "node": {".class": "FuncDef", "arg_kinds": [0, 0], "arg_names": ["self", "spider"], "flags": [], "fullname": "douban.pipelines.MongoPipeline.open_spider", "name": "open_spider", "type": null}}, "process_item": {".class": "SymbolTableNode", "kind": "Mdef", "node": {".class": "FuncDef", "arg_kinds": [0, 0, 0], "arg_names": ["self", "item", "spider"], "flags": [], "fullname": "douban.pipelines.MongoPipeline.process_item", "name": "process_item", "type": null}}}, "protocol_members": null, "tuple_type": null, "type_vars": [], "typeddict_type": null}}, "__doc__": {".class": "SymbolTableNode", "kind": "Gdef", "node": {".class": "Var", "flags": ["is_ready"], "fullname": "douban.pipelines.__doc__", "name": "__doc__", "type": "builtins.str"}}, "__file__": {".class": "SymbolTableNode", "kind": "Gdef", "node": {".class": "Var", "flags": ["is_ready"], "fullname": "douban.pipelines.__file__", "name": "__file__", "type": "builtins.str"}}, "__name__": {".class": "SymbolTableNode", "kind": "Gdef", "node": {".class": "Var", "flags": ["is_ready"], "fullname": "douban.pipelines.__name__", "name": "__name__", "type": "builtins.str"}}, "__package__": {".class": "SymbolTableNode", "kind": "Gdef", "node": {".class": "Var", "flags": ["is_ready"], "fullname": "douban.pipelines.__package__", "name": "__package__", "type": "builtins.str"}}, "pymongo": {".class": "SymbolTableNode", "kind": "Gdef", "node": {".class": "Var", "flags": ["is_ready", "is_suppressed_import"], "fullname": "douban.pipelines.pymongo", "name": "pymongo", "type": {".class": "AnyType"}}}}, "path": "/Users/yuan-hang/Code/scrapy/douban/douban/pipelines.py"}
